setup.py
kt_distributions/Binomialdistribution.py
kt_distributions/Gaussiandistribution.py
kt_distributions/Generaldistribution.py
kt_distributions/__init__.py
kt_distributions.egg-info/PKG-INFO
kt_distributions.egg-info/SOURCES.txt
kt_distributions.egg-info/dependency_links.txt
kt_distributions.egg-info/not-zip-safe
kt_distributions.egg-info/top_level.txt